zarrier/__init__.py
zarrier/function.py
zarrier/log.py
zarrier/number.py
zarrier/string.py
zarrier/test.py
zarrier/timer.py
zarrier/data/__init__.py
zarrier/data/base.py
zarrier/data/config.py
zarrier/data/dataclass.py
zarrier/data/naclass.py
zarrier/data/zconfig.py
zarrier/devices/__init__.py
zarrier/devices/base.py
zarrier/devices/mpsizectors.py
zarrier/devices/robots/__init__.py
zarrier/devices/robots/coordinate_system.py
zarrier/image/__init__.py
zarrier/image/base.py
zarrier/image/calibration.py
zarrier/image/cv2.py
zarrier/image/image_loader.py
zarrier/image/image_size.py
zarrier/math/__init__.py
zarrier/math/base.py
zarrier/math/multidim_point.py
zarrier/math/optimize.py
zarrier/math/utils.py
zarrier/math/geometry/__init__.py
zarrier/math/geometry/plane/__init__.py
zarrier/math/geometry/plane/line.py
zarrier/math/geometry/plane/point.py
zarrier/math/geometry/plane/polygon.py
zarrier/z3d/3d_test.py
zarrier/z3d/__init__.py
zarrier/z3d/addon_functions.py
zarrier/z3d/canvas.py
zarrier/z3d/function.py
zarrier/z3d/mainwindow.py
zarrier/z3d/mpsize_cloud.py
zarrier_python-1.1.7.dist-info/METADATA
zarrier_python-1.1.7.dist-info/WHEEL
zarrier_python-1.1.7.dist-info/top_level.txt
zarrier_python-1.1.7.dist-info/RECORD
