Metadata-Version: 2.1
Name: zarrier-python
Version: 1.1.7
Summary: Mass tools for computer vision projects
Home-page: http://127.0.0.1
Author: homo-zhou
Author-email: 408088242@qq.com
Requires-Dist: numpy
Requires-Dist: opencv-python
Requires-Dist: tqdm
